paylink_mcp_client/__init__.py
paylink_mcp_client/client.py
paylink_mcp_client-0.1.0.dist-info/METADATA
paylink_mcp_client-0.1.0.dist-info/WHEEL
paylink_mcp_client-0.1.0.dist-info/licenses/LICENSE
paylink_mcp_client-0.1.0.dist-info/RECORD
